{
"ons":{
"label":"Population Projections for England and Wales, by local authority",
"source":"Office for National Statistics",
"updated":"2014-10-01",
"area": {
"code":"K04000001",
"label":"England and Wales"
},
"time": {
"label":"2016-2017",
"index":["2016",  "2017"]
},
"concept":{
"label":["population", "% of population"],
"units":["count", "%"],
"max":[       40004,         0.74]
},
"sums":{
"series1":[     2678258,      2678166],
"series2":[     2747483,      2747204]
},
"dimension":{
"label":"age",
"index":["0", "1", "2", "3", "4", "5", "6", "7", "8", "9", "10", "11", "12", "13", "14", "15", "16", "17", "18", "19", "20", "21", "22", "23", "24", "25", "26", "27", "28", "29", "30", "31", "32", "33", "34", "35", "36", "37", "38", "39", "40", "41", "42", "43", "44", "45", "46", "47", "48", "49", "50", "51", "52", "53", "54", "55", "56", "57", "58", "59", "60", "61", "62", "63", "64", "65", "66", "67", "68", "69", "70", "71", "72", "73", "74", "75", "76", "77", "78", "79", "80", "81", "82", "83", "84", "85", "86", "87", "88", "89", "90+"]
},
"series":["male", "female"],
"value":[[[[       33194,        0.61],[       33204,        0.61]],
[[       33071,        0.61],[       33066,        0.61]],
[[       33580,        0.62],[       33597,        0.62]],
[[       34275,        0.63],[       34242,        0.63]],
[[       35420,        0.65],[       35396,        0.65]],
[[       34748,        0.64],[       34707,        0.64]],
[[       34660,        0.64],[       34662,        0.64]],
[[       34364,        0.63],[       34351,        0.63]],
[[       34409,        0.63],[       34412,        0.63]],
[[       33246,        0.61],[       33251,        0.61]],
[[       32933,        0.61],[       32931,        0.61]],
[[       31321,        0.58],[       31301,        0.58]],
[[       30918,        0.57],[       30932,        0.57]],
[[       29886,        0.55],[       29910,        0.55]],
[[       29704,        0.55],[       29707,        0.55]],
[[       29845,        0.55],[       29856,        0.55]],
[[       30945,        0.57],[       30958,        0.57]],
[[       32816,         0.6],[       32804,         0.6]],
[[       33239,        0.61],[       33204,        0.61]],
[[       37683,        0.69],[       37626,        0.69]],
[[       39569,        0.73],[       39615,        0.73]],
[[       38582,        0.71],[       38510,        0.71]],
[[       39559,        0.73],[       39532,        0.73]],
[[       39758,        0.73],[       39762,        0.73]],
[[       39649,        0.73],[       39615,        0.73]],
[[       39942,        0.74],[       40004,        0.74]],
[[       38284,        0.71],[       38254,        0.71]],
[[       36167,        0.67],[       36149,        0.67]],
[[       36277,        0.67],[       36341,        0.67]],
[[       34295,        0.63],[       34385,        0.63]],
[[       34908,        0.64],[       34906,        0.64]],
[[       34832,        0.64],[       34844,        0.64]],
[[       33775,        0.62],[       33841,        0.62]],
[[       33403,        0.62],[       33383,        0.62]],
[[       33702,        0.62],[       33682,        0.62]],
[[       33508,        0.62],[       33634,        0.62]],
[[       34126,        0.63],[       34099,        0.63]],
[[       32703,         0.6],[       32695,         0.6]],
[[       29962,        0.55],[       30044,        0.55]],
[[       29604,        0.55],[       29560,        0.54]],
[[       30769,        0.57],[       30771,        0.57]],
[[       31698,        0.58],[       31705,        0.58]],
[[       32164,        0.59],[       32140,        0.59]],
[[       34435,        0.63],[       34445,        0.63]],
[[       36333,        0.67],[       36291,        0.67]],
[[       38138,         0.7],[       38131,         0.7]],
[[       37052,        0.68],[       37076,        0.68]],
[[       37398,        0.69],[       37395,        0.69]],
[[       37686,        0.69],[       37692,        0.69]],
[[       38307,        0.71],[       38248,         0.7]],
[[       37938,         0.7],[       37893,         0.7]],
[[       38130,         0.7],[       38148,         0.7]],
[[       38132,         0.7],[       38152,         0.7]],
[[       37487,        0.69],[       37468,        0.69]],
[[       36823,        0.68],[       36795,        0.68]],
[[       35614,        0.66],[       35646,        0.66]],
[[       34467,        0.64],[       34438,        0.63]],
[[       33253,        0.61],[       33247,        0.61]],
[[       33007,        0.61],[       32974,        0.61]],
[[       31974,        0.59],[       31987,        0.59]],
[[       30747,        0.57],[       30773,        0.57]],
[[       29186,        0.54],[       29167,        0.54]],
[[       29733,        0.55],[       29728,        0.55]],
[[       29202,        0.54],[       29194,        0.54]],
[[       27947,        0.52],[       27949,        0.52]],
[[       28417,        0.52],[       28414,        0.52]],
[[       28491,        0.53],[       28451,        0.52]],
[[       29561,        0.54],[       29562,        0.54]],
[[       30669,        0.57],[       30660,        0.57]],
[[       33477,        0.62],[       33483,        0.62]],
[[       24883,        0.46],[       24900,        0.46]],
[[       24096,        0.44],[       24093,        0.44]],
[[       23795,        0.44],[       23785,        0.44]],
[[       21611,         0.4],[       21615,         0.4]],
[[       18663,        0.34],[       18673,        0.34]],
[[       16919,        0.31],[       16902,        0.31]],
[[       17483,        0.32],[       17491,        0.32]],
[[       16896,        0.31],[       16890,        0.31]],
[[       16634,        0.31],[       16641,        0.31]],
[[       15151,        0.28],[       15156,        0.28]],
[[       13858,        0.26],[       13874,        0.26]],
[[       12748,        0.23],[       12736,        0.23]],
[[       11464,        0.21],[       11460,        0.21]],
[[       10208,        0.19],[       10195,        0.19]],
[[        9182,        0.17],[        9186,        0.17]],
[[        8225,        0.15],[        8224,        0.15]],
[[        6892,        0.13],[        6892,        0.13]],
[[        5987,        0.11],[        5996,        0.11]],
[[        4961,        0.09],[        4959,        0.09]],
[[        4199,        0.08],[        4197,        0.08]],
[[       13306,        0.25],[       13306,        0.25]]],
[[[       31246,        0.58],[       31250,        0.58]],
[[       31781,        0.59],[       31765,        0.59]],
[[       31940,        0.59],[       31921,        0.59]],
[[       32806,         0.6],[       32821,         0.6]],
[[       34030,        0.63],[       33975,        0.63]],
[[       32906,        0.61],[       32958,        0.61]],
[[       33227,        0.61],[       33267,        0.61]],
[[       32841,        0.61],[       32887,        0.61]],
[[       32632,         0.6],[       32631,         0.6]],
[[       31880,        0.59],[       31851,        0.59]],
[[       31582,        0.58],[       31548,        0.58]],
[[       30470,        0.56],[       30446,        0.56]],
[[       29575,        0.55],[       29600,        0.55]],
[[       28770,        0.53],[       28781,        0.53]],
[[       28372,        0.52],[       28365,        0.52]],
[[       28849,        0.53],[       28869,        0.53]],
[[       29582,        0.55],[       29565,        0.54]],
[[       30637,        0.56],[       30613,        0.56]],
[[       32125,        0.59],[       32142,        0.59]],
[[       36971,        0.68],[       36987,        0.68]],
[[       38229,         0.7],[       38107,         0.7]],
[[       36711,        0.68],[       36698,        0.68]],
[[       37714,         0.7],[       37669,        0.69]],
[[       37745,         0.7],[       37745,         0.7]],
[[       38039,         0.7],[       38128,         0.7]],
[[       37527,        0.69],[       37398,        0.69]],
[[       35745,        0.66],[       35753,        0.66]],
[[       34973,        0.64],[       34956,        0.64]],
[[       36289,        0.67],[       36372,        0.67]],
[[       35356,        0.65],[       35488,        0.65]],
[[       35201,        0.65],[       35189,        0.65]],
[[       35300,        0.65],[       35280,        0.65]],
[[       34515,        0.64],[       34399,        0.63]],
[[       34310,        0.63],[       34342,        0.63]],
[[       34311,        0.63],[       34315,        0.63]],
[[       34572,        0.64],[       34702,        0.64]],
[[       34347,        0.63],[       34389,        0.63]],
[[       32696,         0.6],[       32657,         0.6]],
[[       29945,        0.55],[       29920,        0.55]],
[[       29411,        0.54],[       29436,        0.54]],
[[       31014,        0.57],[       30976,        0.57]],
[[       31418,        0.58],[       31462,        0.58]],
[[       32730,         0.6],[       32774,         0.6]],
[[       34677,        0.64],[       34664,        0.64]],
[[       36798,        0.68],[       36750,        0.68]],
[[       38659,        0.71],[       38635,        0.71]],
[[       37822,         0.7],[       37822,         0.7]],
[[       38602,        0.71],[       38540,        0.71]],
[[       38430,        0.71],[       38450,        0.71]],
[[       38328,        0.71],[       38316,        0.71]],
[[       38303,        0.71],[       38251,        0.71]],
[[       38598,        0.71],[       38588,        0.71]],
[[       38508,        0.71],[       38507,        0.71]],
[[       37899,         0.7],[       37948,         0.7]],
[[       37205,        0.69],[       37137,        0.68]],
[[       36125,        0.67],[       36148,        0.67]],
[[       35012,        0.65],[       34985,        0.64]],
[[       34131,        0.63],[       34139,        0.63]],
[[       33856,        0.62],[       33847,        0.62]],
[[       32409,         0.6],[       32388,         0.6]],
[[       31486,        0.58],[       31466,        0.58]],
[[       29830,        0.55],[       29806,        0.55]],
[[       30078,        0.55],[       30078,        0.55]],
[[       29767,        0.55],[       29741,        0.55]],
[[       28964,        0.53],[       28955,        0.53]],
[[       29361,        0.54],[       29374,        0.54]],
[[       30109,        0.55],[       30111,        0.56]],
[[       30480,        0.56],[       30467,        0.56]],
[[       32664,         0.6],[       32685,         0.6]],
[[       35355,        0.65],[       35318,        0.65]],
[[       26846,        0.49],[       26828,        0.49]],
[[       26538,        0.49],[       26543,        0.49]],
[[       25680,        0.47],[       25698,        0.47]],
[[       23722,        0.44],[       23713,        0.44]],
[[       21442,         0.4],[       21419,        0.39]],
[[       19760,        0.36],[       19718,        0.36]],
[[       20737,        0.38],[       20743,        0.38]],
[[       20328,        0.37],[       20335,        0.37]],
[[       19752,        0.36],[       19768,        0.36]],
[[       18861,        0.35],[       18869,        0.35]],
[[       17931,        0.33],[       17932,        0.33]],
[[       16798,        0.31],[       16796,        0.31]],
[[       15434,        0.28],[       15443,        0.28]],
[[       14196,        0.26],[       14196,        0.26]],
[[       13432,        0.25],[       13434,        0.25]],
[[       12633,        0.23],[       12632,        0.23]],
[[       11572,        0.21],[       11588,        0.21]],
[[        9987,        0.18],[        9974,        0.18]],
[[        8685,        0.16],[        8688,        0.16]],
[[        7716,        0.14],[        7709,        0.14]],
[[       31657,        0.58],[       31665,        0.58]]]]}}
